tf/ocr/__init__.py
tf/ocr/__init__.pyi
tf/ocr/images/__init__.py
tf/ocr/images/images.py
tf/ocr/labels/__init__.py
tf/ocr/labels/labels.py
tf/ocr/serving/__init__.py
tf/ocr/serving/pipeline.py
tf/ocr/tfrecords/__init__.py
tf/ocr/tfrecords/__init__.pyi
tf/ocr/tfrecords/datasets.py
tf/ocr/tfrecords/examples.py
tf/ocr/tfrecords/params.py
tf/ocr/tfrecords/params.pyi
tf/ocr/utils/__init__.py
tf/ocr/utils/logits.py
tf/ocr/utils/postprocess.py
tf/ocr/vocab/__init__.py
tf/ocr/vocab/test_vocab.py
tf/ocr/vocab/vocab.py
tf_ocr-0.1.7.dist-info/METADATA
tf_ocr-0.1.7.dist-info/WHEEL
tf_ocr-0.1.7.dist-info/top_level.txt
tf_ocr-0.1.7.dist-info/RECORD
