Metadata-Version: 2.1
Name: tf-ocr
Version: 0.1.7
Summary: Tools for OCR in tensorflow. Typed with `jaxtyping`
Author-email: Marcel Claramunt <marcel@moveread.com>
Requires-Python: >=3.10
Requires-Dist: jaxtyping
Requires-Dist: tf-ctc
Requires-Dist: tf-tools
Requires-Dist: tensorflow
Requires-Dist: tf-keras
Requires-Dist: typing-extensions
